asgi_babel/__init__.py
asgi_babel/py.typed
asgi_babel-0.11.0.dist-info/licenses/LICENSE
asgi_babel-0.11.0.dist-info/METADATA
asgi_babel-0.11.0.dist-info/WHEEL
asgi_babel-0.11.0.dist-info/top_level.txt
asgi_babel-0.11.0.dist-info/RECORD
