Metadata-Version: 2.4
Name: asgi-babel
Version: 0.11.0
Summary: Internationalization (i18n) support for ASGI applications
Author-email: Kirill Klenov <horneds@gmail.com>
License: MIT License
Project-URL: homepage, https://github.com/klen/asgi-babel
Project-URL: repository, https://github.com/klen/asgi-babel
Keywords: locale,i18n,l10n,babel,gettext,translation,asyncio,trio,asgi
Classifier: Topic :: Software Development :: Internationalization
Classifier: Development Status :: 5 - Production/Stable
Classifier: Intended Audience :: Developers
Classifier: License :: OSI Approved :: MIT License
Classifier: Programming Language :: Python
Classifier: Programming Language :: Python :: 3
Classifier: Programming Language :: Python :: 3.10
Classifier: Programming Language :: Python :: 3.11
Classifier: Programming Language :: Python :: 3.12
Classifier: Programming Language :: Python :: 3.13
Classifier: Programming Language :: Python :: 3.14
Classifier: Topic :: Internet :: WWW/HTTP
Classifier: Framework :: AsyncIO
Classifier: Framework :: Trio
Requires-Python: >=3.10
License-File: LICENSE
Requires-Dist: asgi-tools>=0.73.0
Requires-Dist: babel
Provides-Extra: tests
Requires-Dist: pytest; extra == "tests"
Requires-Dist: pytest-aio[curio,trio]>=1.1.0; extra == "tests"
Requires-Dist: pytest-mypy; implementation_name == "cpython" and extra == "tests"
Requires-Dist: ruff; extra == "tests"
Provides-Extra: example
Requires-Dist: uvicorn; extra == "example"
Provides-Extra: dev
Requires-Dist: bump2version; extra == "dev"
Requires-Dist: tox; extra == "dev"
Requires-Dist: pre-commit; extra == "dev"
Dynamic: license-file
